goamazondownloader/__init__.py
goamazondownloader/_downloader.py
goamazondownloader/_exceptions.py
goamazondownloader/constants.py
goamazondownloader/sbandradar/__init__.py
goamazondownloader/sbandradar/_sbandradar.py
goamazondownloader/vlfsensor/__init__.py
goamazondownloader/vlfsensor/_vlfsensor.py
goamazondownloader-0.1.4.dist-info/LICENSE
goamazondownloader-0.1.4.dist-info/METADATA
goamazondownloader-0.1.4.dist-info/WHEEL
goamazondownloader-0.1.4.dist-info/top_level.txt
goamazondownloader-0.1.4.dist-info/RECORD
