Metadata-Version: 2.1
Name: goamazondownloader
Version: 0.1.4
Summary: A library python to download data of campaign GoAmazon
Home-page: https://github.com/AdrianoPereira/goamazondownloader
Author: Adriano P. Almeida
Author-email: adriano.almeida@inpe.br
License: MIT
Project-URL: Bug Reports, https://github.com/AdrianoPereira/goamazondownloader/issues
Project-URL: Say Thanks!, http://adrianopereira.github.io
Project-URL: Source, https://github.com/AdrianoPereira/goamazondownloader
Keywords: data weather,goamazon,sipam,starnet
Platform: UNKNOWN
Classifier: Development Status :: 3 - Alpha
Classifier: Programming Language :: Python :: 3
Classifier: Programming Language :: Python :: 3.5
Classifier: Programming Language :: Python :: 3.6
Classifier: Programming Language :: Python :: 3.7
Classifier: Programming Language :: Python :: 3.8
Classifier: Programming Language :: Python :: 3 :: Only
Requires-Python: >=3.5, <4
Requires-Dist: requests
Requires-Dist: beautifulsoup4
